easy_openstack_api/SelfDefinedClient.py
easy_openstack_api/__init__.py
easy_openstack_api/openstack_api.py
easy_openstack_api/openstack_resources.py
easy_openstack_api-1.1.7.dist-info/METADATA
easy_openstack_api-1.1.7.dist-info/WHEEL
easy_openstack_api-1.1.7.dist-info/top_level.txt
easy_openstack_api-1.1.7.dist-info/RECORD
