Metadata-Version: 2.1
Name: easy-openstack-api
Version: 1.1.7
Summary: some one step openstack api
Home-page: https://gitlabe1.ext.net.nokia.com/rolv/easy-openstack-api
Author: lv yan
Author-email: rocky.lv@nokia-sbell.com
License: UNKNOWN
Keywords: openstack api
Platform: UNKNOWN
Requires-Dist: python-openstackclient
Requires-Dist: python-heatclient
Requires-Dist: python-neutronclient
